odoo8_addon_event_track_generate-8.0.2.0.0.99.dev15-py2.7-nspkg.pth
odoo_addons/event_track_generate/__openerp__.py
odoo_addons/event_track_generate/__init__.py
odoo_addons/event_track_generate/README.rst
odoo_addons/event_track_generate/i18n/es.po
odoo_addons/event_track_generate/wizards/wizard_generator.py
odoo_addons/event_track_generate/wizards/wizard_generator_view.xml
odoo_addons/event_track_generate/wizards/__init__.py
odoo_addons/event_track_generate/tests/test_generator.py
odoo_addons/event_track_generate/tests/__init__.py
odoo_addons/event_track_generate/static/description/icon.svg
odoo_addons/event_track_generate/static/description/icon.png
odoo8_addon_event_track_generate-8.0.2.0.0.99.dev15.dist-info/top_level.txt
odoo8_addon_event_track_generate-8.0.2.0.0.99.dev15.dist-info/WHEEL
odoo8_addon_event_track_generate-8.0.2.0.0.99.dev15.dist-info/RECORD
odoo8_addon_event_track_generate-8.0.2.0.0.99.dev15.dist-info/metadata.json
odoo8_addon_event_track_generate-8.0.2.0.0.99.dev15.dist-info/DESCRIPTION.rst
odoo8_addon_event_track_generate-8.0.2.0.0.99.dev15.dist-info/METADATA
odoo8_addon_event_track_generate-8.0.2.0.0.99.dev15.dist-info/namespace_packages.txt
