Metadata-Version: 2.0
Name: odoo8-addon-event-track-generate
Version: 8.0.2.0.0.99.dev15
Summary: Generate a bunch of event tracks at once
Home-page: http://www.grupoesoc.es
Author: UNKNOWN
Author-email: UNKNOWN
License: AGPL-3
Platform: UNKNOWN
Requires-Dist: odoo (<9.0a,>=8.0a)
Classifier: Programming Language :: Python :: 2.7
Classifier: Framework :: Odoo
Classifier: License :: OSI Approved :: GNU Affero General Public License v3
